black_mesa_library/__init__.py
black_mesa_library/core.py
black_mesa_library2-0.2.0.dist-info/LICENSE
black_mesa_library2-0.2.0.dist-info/METADATA
black_mesa_library2-0.2.0.dist-info/WHEEL
black_mesa_library2-0.2.0.dist-info/top_level.txt
black_mesa_library2-0.2.0.dist-info/RECORD
