Metadata-Version: 2.1
Name: black-mesa-library2
Version: 0.2.0
Summary: Super Secret Stuff
Author: D S
Author-email: dustin.silveri+poc1@gmail.com
Requires-Python: >=3.6
License-File: LICENSE
